mboot/__init__.py
mboot/__main__.py
mboot/commands.py
mboot/errorcodes.py
mboot/exceptions.py
mboot/mcuboot.py
mboot/memories.py
mboot/properties.py
mboot/connection/__init__.py
mboot/connection/base.py
mboot/connection/uart.py
mboot/connection/usb.py
mboot-0.3.0.dist-info/LICENSE
mboot-0.3.0.dist-info/METADATA
mboot-0.3.0.dist-info/WHEEL
mboot-0.3.0.dist-info/entry_points.txt
mboot-0.3.0.dist-info/top_level.txt
mboot-0.3.0.dist-info/RECORD
