Metadata-Version: 2.1
Name: mboot
Version: 0.3.0
Summary: Python module for communication with NXP MCU Bootloader
Home-page: https://github.com/molejar/pyMBoot
Author: Martin Olejar
Author-email: martin.olejar@gmail.com
License: BSD3
Platform: UNKNOWN
Classifier: Programming Language :: Python :: 3.6
Classifier: Programming Language :: Python :: 3.7
Classifier: Programming Language :: Python :: 3.8
Classifier: License :: OSI Approved :: BSD License
Classifier: Operating System :: Microsoft :: Windows
Classifier: Operating System :: POSIX :: Linux
Classifier: Environment :: Console
Classifier: Topic :: Scientific/Engineering
Classifier: Topic :: Software Development :: Embedded Systems
Classifier: Topic :: Utilities
Requires-Python: >=3.6
Requires-Dist: click (==7.0)
Requires-Dist: pyserial (==3.4)
Requires-Dist: bincopy (==16.0.0)
Requires-Dist: easy-enum (==0.3.0)
Requires-Dist: pyusb (==1.0.2)
Requires-Dist: pywinusb (==0.4.2) ; platform_system == "Windows"
